flask_mkdocs/__init__.py
flask_mkdocs/__version__.py
flask_mkdocs/config.py
flask_mkdocs/docs_template/macros.py
flask_mkdocs/docs_template/mkdocs.yml
flask_mkdocs/docs_template/overrides/adminlte3.html
flask_mkdocs/docs_template/overrides/home.html
flask_mkdocs/docs_template/overrides/main.html
flask_mkdocs/docs_template/overrides/timeline.html
flask_mkdocs/docs_template/overrides/.icons/aws/cloudwatch-32.svg
flask_mkdocs/docs_template/overrides/.icons/aws/codepipeline-32.svg
flask_mkdocs/docs_template/overrides/.icons/aws/codepipeline-64.svg
flask_mkdocs/docs_template/overrides/.icons/aws/fargate-32.svg
flask_mkdocs/docs_template/src/FAQ.md
flask_mkdocs/docs_template/src/architectural-decision-records.md
flask_mkdocs/docs_template/src/changelog.md
flask_mkdocs/docs_template/src/commands.md
flask_mkdocs/docs_template/src/index.md
flask_mkdocs/docs_template/src/installation.md
flask_mkdocs/docs_template/src/overview.md
flask_mkdocs/docs_template/src/quickstart.md
flask_mkdocs/docs_template/src/status.md
flask_mkdocs/documentation/__init__.py
flask_mkdocs/documentation/cli.py
flask_mkdocs/documentation/docsample.py
tests/__init__.py
tests/conftest.py
tests/test_documentation.py
flask_mkdocs-0.0.2.dist-info/METADATA
flask_mkdocs-0.0.2.dist-info/WHEEL
flask_mkdocs-0.0.2.dist-info/entry_points.txt
flask_mkdocs-0.0.2.dist-info/top_level.txt
flask_mkdocs-0.0.2.dist-info/RECORD
